boto3_session_cache/__init__.py
boto3_session_cache/boto3_session_cache.py
boto3_session_cache/cache.py
boto3_session_cache-1.0.2.dist-info/DESCRIPTION.rst
boto3_session_cache-1.0.2.dist-info/METADATA
boto3_session_cache-1.0.2.dist-info/RECORD
boto3_session_cache-1.0.2.dist-info/WHEEL
boto3_session_cache-1.0.2.dist-info/metadata.json
boto3_session_cache-1.0.2.dist-info/top_level.txt
